Products.PasswordResetTool-2.2.4-py2.7-nspkg.pth
Products/PasswordResetTool/PasswordResetTool.py
Products/PasswordResetTool/__init__.py
Products/PasswordResetTool/browser.py
Products/PasswordResetTool/configure.zcml
Products/PasswordResetTool/django_random.py
Products/PasswordResetTool/tool.gif
Products/PasswordResetTool/dtml/explainPWResetTool.dtml
Products/PasswordResetTool/interfaces/__init__.py
Products/PasswordResetTool/interfaces/portal_password_reset.py
Products/PasswordResetTool/profiles/default/metadata.xml
Products/PasswordResetTool/profiles/default/skins.xml
Products/PasswordResetTool/profiles/default/toolset.xml
Products/PasswordResetTool/skins/PasswordReset/mail_password_form.pt
Products/PasswordResetTool/skins/PasswordReset/mail_password_form.pt.metadata
Products/PasswordResetTool/skins/PasswordReset/mail_password_response.pt
Products/PasswordResetTool/skins/PasswordReset/mail_password_template.pt
Products/PasswordResetTool/skins/PasswordReset/passwordreset.cpy
Products/PasswordResetTool/skins/PasswordReset/passwordreset.cpy.metadata
Products/PasswordResetTool/skins/PasswordReset/pwreset_action.cpy
Products/PasswordResetTool/skins/PasswordReset/pwreset_action.cpy.metadata
Products/PasswordResetTool/skins/PasswordReset/pwreset_constructURL.py
Products/PasswordResetTool/skins/PasswordReset/pwreset_expired.pt
Products/PasswordResetTool/skins/PasswordReset/pwreset_expired.pt.metadata
Products/PasswordResetTool/skins/PasswordReset/pwreset_finish.pt
Products/PasswordResetTool/skins/PasswordReset/pwreset_finish.pt.metadata
Products/PasswordResetTool/skins/PasswordReset/pwreset_form.cpt
Products/PasswordResetTool/skins/PasswordReset/pwreset_form.cpt.metadata
Products/PasswordResetTool/skins/PasswordReset/pwreset_invalid.pt
Products/PasswordResetTool/skins/PasswordReset/pwreset_invalid.pt.metadata
Products/PasswordResetTool/skins/PasswordReset/registered_notify_template.pt
Products.PasswordResetTool-2.2.4.dist-info/DESCRIPTION.rst
Products.PasswordResetTool-2.2.4.dist-info/METADATA
Products.PasswordResetTool-2.2.4.dist-info/RECORD
Products.PasswordResetTool-2.2.4.dist-info/WHEEL
Products.PasswordResetTool-2.2.4.dist-info/metadata.json
Products.PasswordResetTool-2.2.4.dist-info/namespace_packages.txt
Products.PasswordResetTool-2.2.4.dist-info/top_level.txt
