Metadata-Version: 2.0
Name: Products.PasswordResetTool
Version: 2.2.4
Summary: Password reset tool for Plone
Home-page: https://pypi.python.org/pypi/Products.PasswordResetTool
Author: J. Cameron Cooper
Author-email: prt@jcameroncooper.com
License: GPL
Keywords: password reset plone
Platform: UNKNOWN
Classifier: Framework :: Plone
Classifier: Framework :: Plone :: 5.0
Classifier: Framework :: Zope2
Classifier: License :: OSI Approved :: GNU General Public License (GPL)
Classifier: Programming Language :: Python
Classifier: Programming Language :: Python :: 2.7
Requires-Dist: setuptools
Requires-Dist: plone.memoize
Requires-Dist: zope.component
Requires-Dist: zope.i18nmessageid
Requires-Dist: zope.i18n
Requires-Dist: zope.interface
Requires-Dist: Products.CMFPlone
Requires-Dist: Products.CMFCore
Requires-Dist: Acquisition
Requires-Dist: DateTime
Requires-Dist: Zope2
Requires-Dist: plone.app.registry
Provides-Extra: test
Requires-Dist: plone.app.testing; extra == 'test'
